.gitignore
.gitmodules
LICENSE
MANIFEST.in
README.rst
setup.cfg
setup.py
firehsql/LICENSE
firehsql/README.rst
firehsql/__init__.py
firehsql/delete_sql.py
firehsql/field.py
firehsql/filter_by.py
firehsql/insert_sql.py
firehsql/join_sql.py
firehsql/order_by.py
firehsql/schema.py
firehsql/select_sql.py
firehsql/sql.py
firehsql/update_sql.py
firehsql.egg-info/PKG-INFO
firehsql.egg-info/SOURCES.txt
firehsql.egg-info/dependency_links.txt
firehsql.egg-info/top_level.txt
firehsql/expressions/__init__.py
firehsql/expressions/average.py
firehsql/expressions/count.py
firehsql/expressions/expression.py
firehsql/expressions/generic.py
firehsql/expressions/maximum.py
firehsql/expressions/minimum.py
firehsql/expressions/sum.py
firehsql/statements/__init__.py
firehsql/statements/on_conflict_update.py
firehsql/statements/reset_sequence.py
firehsql/statements/statement.py
firehsql/tests/__init__.py
firehsql/tests/test_select_sql_join.py