Metadata-Version: 2.1
Name: firehsql
Version: 1.0.4
Summary: Simple SQL generator.
Home-page: https://github.com/dozymoe/firehsql
Author: Fahri Reza
Author-email: dozymoe@gmail.com
License: MIT
Platform: UNKNOWN
Classifier: License :: OSI Approved :: MIT License
Classifier: Programming Language :: Python
Classifier: Programming Language :: Python :: 3
Classifier: Programming Language :: Python :: 3.6
Classifier: Programming Language :: Python :: Implementation :: CPython
Classifier: Programming Language :: Python :: Implementation :: PyPy
Requires-Python: >=2.7.0
